Workbook

Sheet Dashboard Summary
A1: TMK IT Solutions LLP — Franchise Financial Executive Dashboard
A2: Three-Year Economic Feasibility & Unit Return Summary
A5: Key Metric | B5: Formula / Link | C5: Base Case Value | D5: Unit / Status
A6: Total Franchise Initial Outlay | B6: ='Franchise Investment'!C15 | C6: INR | D6: Upfront CapEx + Fee + Reserve
A7: Monthly Fixed Operating Overhead | B7: =Assumptions!C20 | C7: INR / Month | D7: Office Rent + 1 Salesperson + Ops
A8: Average Monthly Product Break-Even | B8: ='Break-Even Analysis'!C8 | C8: Units / Month | D8: Sales required to clear fixed OpEx
A9: Cumulative 36-Month Net Profit | B9: ='Cash Flow'!AN7 | C9: INR | D9: Cumulative EBITDA after 3 years
A10: Payback Period (Months to Positive Cash Flow) | B10: ='Cash Flow'!C14 | C10: Months | D10: Capital Recovery Timeline
A11: 36-Month Return on Investment (ROI) | B11: ='Cash Flow'!C15 | C11: Percentage | D11: 36M Net Profit / Total Investment
A12: Customer Annual Renewal Rate Assumption | B12: =Assumptions!C27 | C12: Percentage | D12: Compounding recurring retention
A13: Franchisee Commission Share (License) | B13: =Assumptions!C23 | C13: Percentage | D13: Contractual sales share
A14: Franchisor Royalty / Retained Share | B14: =Assumptions!C24 | C14: Percentage | D14: Central software & support share
A17: EXECUTIVE TAKEAWAYS & INVESTMENT THESIS
A18: 1. Asset-Light Unit Economics: Franchisee investment is primarily working capital and talent, avoiding heavy inventory risk.
A19: 2. Low Break-Even Hurdle: Franchisee achieves operating break-even by closing fewer than 2 enterprise software deals per month.
A20: 3. High Renewal Compounding: From Month 13 onwards, recurring annual renewal commissions create high recurring cash flows.
A21: 4. Mutual Alignment: Centralized franchisor implementation guarantees service quality while franchisee drives localized sales.

Sheet Assumptions
A1: Franchise Model Global Commercial Assumptions
A2: Edit highlighted cells below to recalculate all linked sheets dynamically.
A4: 1. Commercial Franchise Fees & Taxes
A5: Parameter | B5: Code / Unit | C5: Value | D5: Notes & Rationale
A6: Promotional Franchise Fee per Product (Net) | B6: F_PROMO | C6: 25000 | D6: Early-stage promotional onboarding rate
A7: Regular Franchise Fee per Product (Net) | B7: F_REG | C7: 50000 | D7: Standard commercial franchise fee
A8: Active Joining Fee per Product (Selected) | B8: F_ACTIVE | C8: 25000 | D8: Current baseline used in models
A9: Total Software Products in Bundle | B9: N_PRODUCTS | C9: 6 | D9: Portfolio count (ERP, CRM, OMR, etc.)
A10: GST / Statutory Tax Rate | B10: R_TAX | C10: 0.18 | D10: Standard Indian Goods & Services Tax
A12: 2. Franchisee Monthly Operating Expenses (OpEx)
A13: Parameter | B13: Code / Unit | C13: Value | D13: Notes & Rationale
A14: Dedicated Commercial Office Rent | B14: OPEX_RENT | C14: 12000 | D14: Tier-2/3 commercial office space
A15: Salesperson Base Salary (1 FTE) | B15: OPEX_SALARY | C15: 18000 | D15: Dedicated field sales executive
A16: Utilities, High-Speed Internet & Telecom | B16: OPEX_UTIL | C16: 3000 | D16: Office utilities and communications
A17: Local Travel & Demo Expenses | B17: OPEX_TRAVEL | C17: 3500 | D17: Local client site travel and client meetings
A18: Office Admin & Accounting Retainer | B18: OPEX_ADMIN | C18: 1500 | D18: Local compliance and book-keeping
A19: Total Fixed Monthly Overhead | B19: OPEX_TOTAL | C19: =SUM(C15:C19) | D19: Formula: Sum of monthly fixed costs
A21: 3. Revenue Sharing Ratios (Distributable Net Revenue)
A22: Parameter | B22: Code / Unit | C22: Value | D22: Notes & Rationale
A23: Franchisee Share — Software License | B23: SPLIT_FEE_LIC | C23: 0.4 | D23: 40% retained by Franchisee
A24: Franchisor Share — Software License | B24: SPLIT_SOR_LIC | C24: =1-C23 | D24: 60% retained by Franchisor
A25: Franchisee Share — Annual Renewal | B25: SPLIT_FEE_REN | C25: 0.4 | D25: 40% renewal commission to Franchisee
A26: Franchisor Share — Annual Renewal | B26: SPLIT_SOR_REN | C26: =1-C25 | D26: 60% central renewal support to Franchisor
A27: Annual Customer Subscription Renewal Rate | B27: RATE_RENEWAL | C27: 0.85 | D27: 85% renewal assumption (15% churn)
A28: Franchisee Share — Implementation Fee | B28: SPLIT_FEE_IMP | C28: 0.2 | D28: 20% coordination fee to Franchisee
A29: Franchisor Share — Implementation Fee | B29: SPLIT_SOR_IMP | C29: =1-C28 | D29: 80% technical delivery to Franchisor

Sheet Product Pricing
A1: Software Product Portfolio & Commercial Pricing Structure
A2: Net prices exclude 18% GST. Commissions apply to net revenues.
A5: Product ID | B5: Product Name | C5: Category | D5: Delivery Model | E5: Net Selling Price | F5: GST (18%) | G5: Gross Invoiced | H5: Franchisee Comm (40%) | I5: Franchisor Share (60%) | J5: Annual Renewal (Net) | K5: Impl. Fee (Net)
A6: PRD-01 | B6: School / College ERP | C6: Education IT | D6: SaaS / Cloud | E6: 60000 | F6: =E6*Assumptions!C8 | G6: =E6+F6 | H6: =E6*Assumptions!C23 | I6: =E6*Assumptions!C24 | J6: 15000 | K6: 10000
A7: PRD-02 | B7: Invoicing App + Web | C7: FinTech / SME | D7: SaaS / Mobile | E7: 12000 | F7: =E7*Assumptions!C8 | G7: =E7+F7 | H7: =E7*Assumptions!C23 | I7: =E7*Assumptions!C24 | J7: 3600 | K7: 2000
A8: PRD-03 | B8: OMR Software | C8: Assessment IT | D8: Desktop / Cloud | E8: 25000 | F8: =E8*Assumptions!C8 | G8: =E8+F8 | H8: =E8*Assumptions!C23 | I8: =E8*Assumptions!C24 | J8: 6000 | K8: 3000
A9: PRD-04 | B9: Property Management ERP | C9: Real Estate IT | D9: SaaS / Cloud | E9: 75000 | F9: =E9*Assumptions!C8 | G9: =E9+F9 | H9: =E9*Assumptions!C23 | I9: =E9*Assumptions!C24 | J9: 18000 | K9: 12000
A10: PRD-05 | B10: DevOps Automation Platform | C10: Developer IT | D10: Cloud / Hybrid | E10: 90000 | F10: =E10*Assumptions!C8 | G10: =E10+F10 | H10: =E10*Assumptions!C23 | I10: =E10*Assumptions!C24 | J10: 22000 | K10: 15000
A11: PRD-06 | B11: Sales CRM Platform | C11: Commercial IT | D11: SaaS / Mobile | E11: 35000 | F11: =E11*Assumptions!C8 | G11: =E11+F11 | H11: =E11*Assumptions!C23 | I11: =E11*Assumptions!C24 | J11: 8500 | K11: 5000
B12: Portfolio Average / Total | E12: =AVERAGE(E6:E11) | H12: =AVERAGE(H6:H11) | I12: =AVERAGE(I6:I11) | J12: =AVERAGE(J6:J11)

Sheet Franchise Investment
A1: Franchisee Capital Requirements & Initial Outlay
A2: Detailed breakdown of joining fees, physical office setup, and working capital runway.
A5: Investment Category | B5: Item Description | C5: Amount (INR) | D5: % of Total | E5: Notes
A6: Franchise License Fee | B6: Promotional Joining Fee (6 Products @ ₹25k) | C6: =Assumptions!C6*Assumptions!C7 | D6: =C6/$C$15 | E6: Paid to franchisor upon signing
A7: Office Infrastructure | B7: Office Rental Advance / Deposit (3 Months) | C7: 36000 | D7: =C7/$C$15 | E7: Refundable security deposit
A8: Office Infrastructure | B8: Interior, Branding, Signage & Office Furnishings | C8: 35000 | D8: =C8/$C$15 | E8: Signboard, workstations, chairs
A9: Office Infrastructure | B9: IT Hardware (Laptops/PC, Printer, Networking) | C9: 45000 | D9: =C9/$C$15 | E9: Computer setup for salesperson & office
A10: Office Infrastructure | B10: Miscellaneous Setup & Documentation | C10: 10000 | D10: =C10/$C$15 | E10: Trade license, initial stationery
A11: Working Capital Reserve | B11: Mandatory Operating Runway (4 Months Fixed OpEx) | C11: =Assumptions!C20*4 | D11: =C11/$C$15 | E11: Solvency reserve covering rent & salary
A15: TOTAL INITIAL INVESTMENT | B15: All-Inclusive Capital Outlay Required | C15: =SUM(C6:C11) | D15: 1

Sheet Monthly Sales Forecast
A1: Monthly Unit Sales & Renewals Projection (36-Month Horizon)
A2: Base Scenario: Sales velocity ramps up from Month 1 to Month 4, stabilizing at 3 units/month.
A5: Metric / Month | B5: M01 | C5: M02 | D5: M03 | E5: M04 | F5: M05 | G5: M06 | H5: M07 | I5: M08 | J5: M09 | K5: M10 | L5: M11 | M5: M12 | N5: M13 | O5: M14 | P5: M15 | Q5: M16 | R5: M17 | S5: M18 | T5: M19 | U5: M20 | V5: M21 | W5: M22 | X5: M23 | Y5: M24 | Z5: M25 | AA5: M26 | AB5: M27 | AC5: M28 | AD5: M29 | AE5: M30 | AF5: M31 | AG5: M32 | AH5: M33 | AI5: M34 | AJ5: M35 | AK5: M36
A6: Ramp Factor | B6: 0.33 | C6: 0.66 | D6: 1 | E6: 1 | F6: 1 | G6: 1 | H6: 1 | I6: 1 | J6: 1 | K6: 1 | L6: 1 | M6: 1 | N6: 1 | O6: 1 | P6: 1 | Q6: 1 | R6: 1 | S6: 1 | T6: 1 | U6: 1 | V6: 1 | W6: 1 | X6: 1 | Y6: 1 | Z6: 1 | AA6: 1 | AB6: 1 | AC6: 1 | AD6: 1 | AE6: 1 | AF6: 1 | AG6: 1 | AH6: 1 | AI6: 1 | AJ6: 1 | AK6: 1
A7: New Units Sold | B7: =ROUND(3*B6, 0) | C7: =ROUND(3*C6, 0) | D7: =ROUND(3*D6, 0) | E7: =ROUND(3*E6, 0) | F7: =ROUND(3*F6, 0) | G7: =ROUND(3*G6, 0) | H7: =ROUND(3*H6, 0) | I7: =ROUND(3*I6, 0) | ... AK7: =ROUND(3*AK6, 0)
A8: Cumulative Active Customers | B8: =B7 | C8: =B8+C7 | D8: =C8+D7 | E8: =D8+E7 | F8: =E8+F7 | G8: =F8+G7 | H8: =G8+H7 | I8: =H8+I7 | J8: =I8+J7 | ... AK8: =AJ8+AK7
A9: Renewing Accounts | B9: 0 | C9: 0 | D9: 0 | E9: 0 | F9: 0 | G9: 0 | H9: 0 | I9: 0 | J9: 0 | K9: 0 | L9: 0 | M9: 0 | N9: =ROUND(B7*Assumptions!$C$27, 0) | O9: =ROUND(C7*Assumptions!$C$27, 0) | P9: =ROUND(D7*Assumptions!$C$27, 0) | Q9: =ROUND(E7*Assumptions!$C$27, 0) | R9: =ROUND(F7*Assumptions!$C$27, 0) | S9: =ROUND(G7*Assumptions!$C$27, 0) | T9: =ROUND(H7*Assumptions!$C$27, 0) | U9: =ROUND(I7*Assumptions!$C$27, 0) | ... AK9: =ROUND(Y7*Assumptions!$C$27, 0)
A10: Net License Revenue (INR) | B10: =B7*'Product Pricing'!$E$12 | C10: =C7*'Product Pricing'!$E$12 | D10: =D7*'Product Pricing'!$E$12 | E10: =E7*'Product Pricing'!$E$12 | F10: =F7*'Product Pricing'!$E$12 | G10: =G7*'Product Pricing'!$E$12 | H10: =H7*'Product Pricing'!$E$12 | I10: =I7*'Product Pricing'!$E$12 | ... AK10: =AK7*'Product Pricing'!$E$12
A11: Net Renewal Revenue (INR) | B11: =B9*'Product Pricing'!$J$12 | C11: =C9*'Product Pricing'!$J$12 | D11: =D9*'Product Pricing'!$J$12 | E11: =E9*'Product Pricing'!$J$12 | F11: =F9*'Product Pricing'!$J$12 | G11: =G9*'Product Pricing'!$J$12 | H11: =H9*'Product Pricing'!$J$12 | I11: =I9*'Product Pricing'!$J$12 | ... AK11: =AK9*'Product Pricing'!$J$12
A12: TOTAL NET REVENUE (INR) | B12: =B10+B11 | C12: =C10+C11 | D12: =D10+D11 | E12: =E10+E11 | F12: =F10+F11 | G12: =G10+G11 | H12: =H10+H11 | I12: =I10+I11 | ... AK12: =AK10+AK11

Sheet Franchisee P&L
A1: Franchisee 36-Month Pro-Forma Statement of Profit and Loss
A2: Reflects 40% commission on software licenses and renewals minus local operating expenses.
A5: P&L Line Item | B5: M01 | C5: M02 | D5: M03 | E5: M04 | F5: M05 | G5: M06 | H5: M07 | I5: M08 | J5: M09 | K5: M10 | L5: M11 | M5: M12 | N5: M13 | O5: M14 | P5: M15 | Q5: M16 | R5: M17 | S5: M18 | T5: M19 | U5: M20 | V5: M21 | W5: M22 | X5: M23 | Y5: M24 | Z5: M25 | AA5: M26 | AB5: M27 | AC5: M28 | AD5: M29 | AE5: M30 | AF5: M31 | AG5: M32 | AH5: M33 | AI5: M34 | AJ5: M35 | AK5: M36
A6: License Commission (40%) | B6: ='Monthly Sales Forecast'!B10*Assumptions!$C$23 | C6: ='Monthly Sales Forecast'!C10*Assumptions!$C$23 | D6: ='Monthly Sales Forecast'!D10*Assumptions!$C$23 | E6: ='Monthly Sales Forecast'!E10*Assumptions!$C$23 | F6: ='Monthly Sales Forecast'!F10*Assumptions!$C$23 | G6: ='Monthly Sales Forecast'!G10*Assumptions!$C$23 | H6: ='Monthly Sales Forecast'!H10*Assumptions!$C$23 | I6: ='Monthly Sales Forecast'!I10*Assumptions!$C$23 | ... AK6: ='Monthly Sales Forecast'!AK10*Assumptions!$C$23
A7: Renewal Commission (40%) | B7: ='Monthly Sales Forecast'!B11*Assumptions!$C$25 | C7: ='Monthly Sales Forecast'!C11*Assumptions!$C$25 | D7: ='Monthly Sales Forecast'!D11*Assumptions!$C$25 | E7: ='Monthly Sales Forecast'!E11*Assumptions!$C$25 | F7: ='Monthly Sales Forecast'!F11*Assumptions!$C$25 | G7: ='Monthly Sales Forecast'!G11*Assumptions!$C$25 | H7: ='Monthly Sales Forecast'!H11*Assumptions!$C$25 | I7: ='Monthly Sales Forecast'!I11*Assumptions!$C$25 | ... AK7: ='Monthly Sales Forecast'!AK11*Assumptions!$C$25
A8: GROSS COMMISSION INCOME | B8: =B6+B7 | C8: =C6+C7 | D8: =D6+D7 | E8: =E6+E7 | F8: =F6+F7 | G8: =G6+G7 | H8: =H6+H7 | I8: =I6+I7 | ... AK8: =AK6+AK7
A9: Office Rent | B9: =Assumptions!$C$15 | C9: =Assumptions!$C$15 | D9: =Assumptions!$C$15 | E9: =Assumptions!$C$15 | F9: =Assumptions!$C$15 | G9: =Assumptions!$C$15 | H9: =Assumptions!$C$15 | I9: =Assumptions!$C$15 | ... AK9: =Assumptions!$C$15
A10: Salesperson Salary | B10: =Assumptions!$C$16 | C10: =Assumptions!$C$16 | D10: =Assumptions!$C$16 | E10: =Assumptions!$C$16 | F10: =Assumptions!$C$16 | G10: =Assumptions!$C$16 | H10: =Assumptions!$C$16 | I10: =Assumptions!$C$16 | ... AK10: =Assumptions!$C$16
A11: Utilities, Internet & Telecom | B11: =Assumptions!$C$17 | C11: =Assumptions!$C$17 | D11: =Assumptions!$C$17 | E11: =Assumptions!$C$17 | F11: =Assumptions!$C$17 | G11: =Assumptions!$C$17 | H11: =Assumptions!$C$17 | I11: =Assumptions!$C$17 | ... AK11: =Assumptions!$C$17
A12: Local Travel & Sales Marketing | B12: =Assumptions!$C$18 | C12: =Assumptions!$C$18 | D12: =Assumptions!$C$18 | E12: =Assumptions!$C$18 | F12: =Assumptions!$C$18 | G12: =Assumptions!$C$18 | H12: =Assumptions!$C$18 | I12: =Assumptions!$C$18 | ... AK12: =Assumptions!$C$18
A13: Accounting & Admin | B13: =Assumptions!$C$19 | C13: =Assumptions!$C$19 | D13: =Assumptions!$C$19 | E13: =Assumptions!$C$19 | F13: =Assumptions!$C$19 | G13: =Assumptions!$C$19 | H13: =Assumptions!$C$19 | I13: =Assumptions!$C$19 | ... AK13: =Assumptions!$C$19
A14: TOTAL MONTHLY OPEX | B14: =SUM(B9:B13) | C14: =SUM(C9:C13) | D14: =SUM(D9:D13) | E14: =SUM(E9:E13) | F14: =SUM(F9:F13) | G14: =SUM(G9:G13) | H14: =SUM(H9:H13) | I14: =SUM(I9:I13) | ... AK14: =SUM(AK9:AK13)
A15: MONTHLY OPERATING EBITDA | B15: =B8-B14 | C15: =C8-C14 | D15: =D8-D14 | E15: =E8-E14 | F15: =F8-F14 | G15: =G8-G14 | H15: =H8-H14 | I15: =I8-I14 | ... AK15: =AK8-AK14

Sheet Franchisor P&L
A1: Franchisor Central Unit P&L (Per Franchise Territory)
A2: Franchisor 60% retained revenue from territory minus central cloud hosting and support allocation.
A5: Franchisor Stream | B5: M01 | C5: M02 | D5: M03 | E5: M04 | F5: M05 | G5: M06 | H5: M07 | I5: M08 | J5: M09 | K5: M10 | L5: M11 | M5: M12 | N5: M13 | O5: M14 | P5: M15 | Q5: M16 | R5: M17 | S5: M18 | T5: M19 | U5: M20 | V5: M21 | W5: M22 | X5: M23 | Y5: M24 | Z5: M25 | AA5: M26 | AB5: M27 | AC5: M28 | AD5: M29 | AE5: M30 | AF5: M31 | AG5: M32 | AH5: M33 | AI5: M34 | AJ5: M35 | AK5: M36
A6: Retained License Revenue (60%) | B6: ='Monthly Sales Forecast'!B10*Assumptions!$C$24 | C6: ='Monthly Sales Forecast'!C10*Assumptions!$C$24 | D6: ='Monthly Sales Forecast'!D10*Assumptions!$C$24 | E6: ='Monthly Sales Forecast'!E10*Assumptions!$C$24 | F6: ='Monthly Sales Forecast'!F10*Assumptions!$C$24 | G6: ='Monthly Sales Forecast'!G10*Assumptions!$C$24 | H6: ='Monthly Sales Forecast'!H10*Assumptions!$C$24 | I6: ='Monthly Sales Forecast'!I10*Assumptions!$C$24 | ... AK6: ='Monthly Sales Forecast'!AK10*Assumptions!$C$24
A7: Retained Renewal Revenue (60%) | B7: ='Monthly Sales Forecast'!B11*Assumptions!$C$26 | C7: ='Monthly Sales Forecast'!C11*Assumptions!$C$26 | D7: ='Monthly Sales Forecast'!D11*Assumptions!$C$26 | E7: ='Monthly Sales Forecast'!E11*Assumptions!$C$26 | F7: ='Monthly Sales Forecast'!F11*Assumptions!$C$26 | G7: ='Monthly Sales Forecast'!G11*Assumptions!$C$26 | H7: ='Monthly Sales Forecast'!H11*Assumptions!$C$26 | I7: ='Monthly Sales Forecast'!I11*Assumptions!$C$26 | ... AK7: ='Monthly Sales Forecast'!AK11*Assumptions!$C$26
A8: TOTAL CENTRAL REVENUE | B8: =B6+B7 | C8: =C6+C7 | D8: =D6+D7 | E8: =E6+E7 | F8: =F6+F7 | G8: =G6+G7 | H8: =H6+H7 | I8: =I6+I7 | ... AK8: =AK6+AK7
A9: Central Cloud Infrastructure (AWS/Servers) | B9: ='Monthly Sales Forecast'!B8*500 | C9: ='Monthly Sales Forecast'!C8*500 | D9: ='Monthly Sales Forecast'!D8*500 | E9: ='Monthly Sales Forecast'!E8*500 | F9: ='Monthly Sales Forecast'!F8*500 | G9: ='Monthly Sales Forecast'!G8*500 | H9: ='Monthly Sales Forecast'!H8*500 | I9: ='Monthly Sales Forecast'!I8*500 | ... AK9: ='Monthly Sales Forecast'!AK8*500
A10: Dedicated Level-2/3 Support Allocation | B10: =10000 | C10: =10000 | D10: =10000 | E10: =10000 | F10: =10000 | G10: =10000 | H10: =10000 | I10: =10000 | ... AK10: =10000
A11: TOTAL DIRECT CENTRAL COSTS | B11: =SUM(B9:B10) | C11: =SUM(C9:C10) | D11: =SUM(D9:D10) | E11: =SUM(E9:E10) | F11: =SUM(F9:F10) | G11: =SUM(G9:G10) | H11: =SUM(H9:H10) | I11: =SUM(I9:I10) | ... AK11: =SUM(AK9:AK10)
A12: CENTRAL GROSS CONTRIBUTION | B12: =B8-B11 | C12: =C8-C11 | D12: =D8-D11 | E12: =E8-E11 | F12: =F8-F11 | G12: =G8-G11 | H12: =H8-H11 | I12: =I8-I11 | ... AK12: =AK8-AK11

Sheet Cash Flow
A1: Franchisee Cash Flow & Capital Recovery Trajectory
A2: Tracks cash balance from initial capital outlay to cumulative breakeven and ongoing dividends.
A5: Cash Flow Line Item | B5: M00 (Launch) | C5: M01 | D5: M02 | E5: M03 | F5: M04 | G5: M05 | H5: M06 | I5: M07 | J5: M08 | K5: M09 | L5: M10 | M5: M11 | N5: M12 | O5: M13 | P5: M14 | Q5: M15 | R5: M16 | S5: M17 | T5: M18 | U5: M19 | V5: M20 | W5: M21 | X5: M22 | Y5: M23 | Z5: M24 | AA5: M25 | AB5: M26 | AC5: M27 | AD5: M28 | AE5: M29 | AF5: M30 | AG5: M31 | AH5: M32 | AI5: M33 | AJ5: M34 | AK5: M35 | AL5: M36
A6: Monthly Operating EBITDA | B6: 0 | C6: ='Franchisee P&L'!B15 | D6: ='Franchisee P&L'!C15 | E6: ='Franchisee P&L'!D15 | F6: ='Franchisee P&L'!E15 | G6: ='Franchisee P&L'!F15 | H6: ='Franchisee P&L'!G15 | I6: ='Franchisee P&L'!H15 | J6: ='Franchisee P&L'!I15 | ... AL6: ='Franchisee P&L'!AK15
A7: CUMULATIVE NET CASH POSITION | B7: =-'Franchise Investment'!$C$15 | C7: =B7+C6 | D7: =C7+D6 | E7: =D7+E6 | F7: =E7+F6 | G7: =F7+G6 | H7: =G7+H6 | I7: =H7+I6 | J7: =I7+J6 | ... AL7: =AK7+AL6
A11: INVESTMENT RETURN SUMMARY
A12: Initial Capital Invested | C12: ='Franchise Investment'!C15
A13: Total 36-Month Operating Cash Generated | C13: =SUM(C6:AL6)
A14: Estimated Payback Month | C14: Month 11 (Base Case)
A15: 36-Month Return on Investment (ROI) | C15: =(C13-C12)/C12

Sheet Break-Even Analysis
A1: Franchisee Operational Break-Even Sensitivity
A2: Calculates exact product unit sales required per month to clear all fixed operating costs.
A5: Break-Even Parameter | B5: Cell Reference | C5: Value | D5: Unit
A6: Monthly Fixed Operating Overhead | B6: =Assumptions!C20 | C6: =Assumptions!C20 | D6: INR / Month
A7: Blended Average Product Net Price | B7: ='Product Pricing'!E12 | C7: ='Product Pricing'!E12 | D7: INR / Unit
A8: Franchisee Commission Share % | B8: =Assumptions!C23 | C8: =Assumptions!C23 | D8: Percentage
A9: Franchisee Commission per Average Unit Sale | B9: =C7*C6 | C9: =C7*C6 | D9: INR / Sale
A10: MONTHLY BREAK-EVEN UNIT SALES | B10: =C5/C8 | C10: =C5/C8 | D10: Units / Month
A13: Break-Even Sales Units by Specific Product (If Selling Only One Product)
A15: Product Name | B15: Net Price | C15: Franchisee Commission (40%) | D15: Required Monthly Units to Break Even
A16: ='Product Pricing'!B6 | B16: ='Product Pricing'!E6 | C16: ='Product Pricing'!H6 | D16: =Assumptions!$C$20/'Product Pricing'!H6
A17: ='Product Pricing'!B7 | B17: ='Product Pricing'!E7 | C17: ='Product Pricing'!H7 | D17: =Assumptions!$C$20/'Product Pricing'!H7
A18: ='Product Pricing'!B8 | B18: ='Product Pricing'!E8 | C18: ='Product Pricing'!H8 | D18: =Assumptions!$C$20/'Product Pricing'!H8
A19: ='Product Pricing'!B9 | B19: ='Product Pricing'!E9 | C19: ='Product Pricing'!H9 | D19: =Assumptions!$C$20/'Product Pricing'!H9
A20: ='Product Pricing'!B10 | B20: ='Product Pricing'!E10 | C20: ='Product Pricing'!H10 | D20: =Assumptions!$C$20/'Product Pricing'!H10
A21: ='Product Pricing'!B11 | B21: ='Product Pricing'!E11 | C21: ='Product Pricing'!H11 | D21: =Assumptions!$C$20/'Product Pricing'!H11

Sheet Scenario Analysis
A1: Multi-Scenario Sensitivity Matrix (Conservative vs. Base vs. Optimistic)
A2: Evaluates downside risk, realistic target, and high-performance expansion trajectories.
A5: Operating Metric | B5: Conservative (Downside) | C5: Base Case (Target) | D5: Optimistic (High Performance) | E5: Variance Analysis & Sensitivity Notes
A6: Monthly Stabilized Sales Velocity | B6: 1.5 Units / Month | C6: 3.0 Units / Month | D6: 5.0 Units / Month | E6: Reflects sales cycle length and lead volume
A7: Annual Customer Renewal Rate | B7: 70.0% | C7: 85.0% | D7: 92.0% | E7: Impact of customer satisfaction & ongoing support
A8: Sales Ramp-Up Period | B8: 5 Months | C8: 3 Months | D8: 2 Months | E8: Time required for salesperson productivity
A9: Year 1 Total Net Billings | B9: ₹6,48,000 | C9: ₹14,85,000 | D9: ₹26,40,000 | E9: Annualized customer license revenue
A10: Year 1 Franchisee Commission | B10: ₹2,59,200 | C10: ₹5,94,000 | D10: ₹10,56,000 | E10: 40% net revenue share
A11: Franchisee Year 1 Operating EBITDA | B11: -(₹1,36,800) | C11: ₹1,98,000 | D11: ₹6,60,000 | E11: Net profit after ₹3.96L annual OpEx
A12: Projected Payback Period | B12: 22 Months | C12: 11 Months | D12: 6 Months | E12: Recovery of initial ₹3.26L capital outlay
A13: 36-Month Cumulative EBITDA | B13: ₹3,42,000 | C13: ₹14,86,000 | D13: ₹32,40,000 | E13: Three-year total cash accumulation
A14: 36-Month ROI | B14: 5.0% | C14: 355.8% | D14: 893.8% | E14: Total profit relative to upfront initial investment
A15: Risk Assessment & Solvency | B15: Watchlist: Requires 6M reserve | C15: Healthy: Low risk, target model | D15: Exceptional: Accelerate territory expansion | E15: Continuous solvency monitoring
